opthub_runner/__init__.py
opthub_runner/converter.py
opthub_runner/docker_executor.py
opthub_runner/evaluator.py
opthub_runner-1.0.14.dist-info/METADATA
opthub_runner-1.0.14.dist-info/WHEEL
opthub_runner-1.0.14.dist-info/RECORD
